fastar-0.5.0.dist-info/METADATA
fastar-0.5.0.dist-info/WHEEL
fastar-0.5.0.dist-info/licenses/LICENSE
fastar/__init__.py
fastar/__init__.pyi
fastar/fastar.cpython-314-x86_64-linux-gnu.so
fastar/py.typed
fastar-0.5.0.dist-info/RECORD
